{
  "timestamp": "2025-12-21T02:44:25.873Z",
  "nodesByCountry": [
    {
      "countryCode": "US",
      "nodeCount": 1261
    },
    {
      "countryCode": "DE",
      "nodeCount": 316
    },
    {
      "countryCode": "IE",
      "nodeCount": 158
    },
    {
      "countryCode": "PK",
      "nodeCount": 144
    },
    {
      "countryCode": "FR",
      "nodeCount": 131
    },
    {
      "countryCode": "GB",
      "nodeCount": 115
    },
    {
      "countryCode": "CA",
      "nodeCount": 106
    },
    {
      "countryCode": "SG",
      "nodeCount": 82
    },
    {
      "countryCode": "NL",
      "nodeCount": 73
    },
    {
      "countryCode": "FI",
      "nodeCount": 69
    },
    {
      "countryCode": "AT",
      "nodeCount": 50
    },
    {
      "countryCode": "IN",
      "nodeCount": 49
    },
    {
      "countryCode": "JP",
      "nodeCount": 43
    },
    {
      "countryCode": "AU",
      "nodeCount": 41
    },
    {
      "countryCode": "ID",
      "nodeCount": 38
    },
    {
      "countryCode": "PL",
      "nodeCount": 36
    },
    {
      "countryCode": "IT",
      "nodeCount": 35
    },
    {
      "countryCode": "AE",
      "nodeCount": 30
    },
    {
      "countryCode": "CH",
      "nodeCount": 26
    },
    {
      "countryCode": "ES",
      "nodeCount": 26
    },
    {
      "countryCode": "HK",
      "nodeCount": 20
    },
    {
      "countryCode": "SA",
      "nodeCount": 17
    },
    {
      "countryCode": "BE",
      "nodeCount": 16
    },
    {
      "countryCode": "BR",
      "nodeCount": 15
    },
    {
      "countryCode": "SE",
      "nodeCount": 14
    },
    {
      "countryCode": "KR",
      "nodeCount": 14
    },
    {
      "countryCode": "CZ",
      "nodeCount": 12
    },
    {
      "countryCode": "PT",
      "nodeCount": 12
    },
    {
      "countryCode": "GR",
      "nodeCount": 10
    },
    {
      "countryCode": "CN",
      "nodeCount": 9
    },
    {
      "countryCode": "BD",
      "nodeCount": 9
    },
    {
      "countryCode": "NO",
      "nodeCount": 8
    },
    {
      "countryCode": "RO",
      "nodeCount": 7
    },
    {
      "countryCode": "IL",
      "nodeCount": 7
    },
    {
      "countryCode": "LT",
      "nodeCount": 7
    },
    {
      "countryCode": "MX",
      "nodeCount": 7
    },
    {
      "countryCode": "VN",
      "nodeCount": 7
    },
    {
      "countryCode": "HR",
      "nodeCount": 6
    },
    {
      "countryCode": "ZA",
      "nodeCount": 5
    },
    {
      "countryCode": "BG",
      "nodeCount": 5
    },
    {
      "countryCode": "TR",
      "nodeCount": 5
    },
    {
      "countryCode": "PH",
      "nodeCount": 4
    },
    {
      "countryCode": "UA",
      "nodeCount": 4
    },
    {
      "countryCode": "NG",
      "nodeCount": 4
    },
    {
      "countryCode": "TW",
      "nodeCount": 4
    },
    {
      "countryCode": "CO",
      "nodeCount": 4
    },
    {
      "countryCode": "RU",
      "nodeCount": 4
    },
    {
      "countryCode": "CY",
      "nodeCount": 3
    },
    {
      "countryCode": "OM",
      "nodeCount": 3
    },
    {
      "countryCode": "EE",
      "nodeCount": 3
    },
    {
      "countryCode": "HU",
      "nodeCount": 3
    },
    {
      "countryCode": "TH",
      "nodeCount": 3
    },
    {
      "countryCode": "LV",
      "nodeCount": 3
    },
    {
      "countryCode": "PR",
      "nodeCount": 2
    },
    {
      "countryCode": "LU",
      "nodeCount": 2
    },
    {
      "countryCode": "BH",
      "nodeCount": 2
    },
    {
      "countryCode": "IS",
      "nodeCount": 2
    },
    {
      "countryCode": "AR",
      "nodeCount": 2
    },
    {
      "countryCode": "QA",
      "nodeCount": 2
    },
    {
      "countryCode": "MY",
      "nodeCount": 2
    },
    {
      "countryCode": "MA",
      "nodeCount": 2
    },
    {
      "countryCode": "SK",
      "nodeCount": 2
    },
    {
      "countryCode": "SI",
      "nodeCount": 2
    },
    {
      "countryCode": "UY",
      "nodeCount": 2
    },
    {
      "countryCode": "DO",
      "nodeCount": 2
    },
    {
      "countryCode": "KY",
      "nodeCount": 1
    },
    {
      "countryCode": "ME",
      "nodeCount": 1
    },
    {
      "countryCode": "CD",
      "nodeCount": 1
    },
    {
      "countryCode": "KZ",
      "nodeCount": 1
    },
    {
      "countryCode": "KE",
      "nodeCount": 1
    },
    {
      "countryCode": "DK",
      "nodeCount": 1
    },
    {
      "countryCode": "MO",
      "nodeCount": 1
    },
    {
      "countryCode": "CL",
      "nodeCount": 1
    },
    {
      "countryCode": "NZ",
      "nodeCount": 1
    },
    {
      "countryCode": "KW",
      "nodeCount": 1
    },
    {
      "countryCode": "MT",
      "nodeCount": 1
    },
    {
      "countryCode": "VE",
      "nodeCount": 1
    },
    {
      "countryCode": "MV",
      "nodeCount": 1
    },
    {
      "countryCode": "BO",
      "nodeCount": 1
    },
    {
      "countryCode": "PY",
      "nodeCount": 1
    }
  ],
  "totalCountries": 80,
  "metadata": {
    "source": "Nodely Node Telemetry Service",
    "description": "Distribution of Algorand nodes by country (last 24h)"
  }
}